pencompy/__init__.py
pencompy/pencom.py
pencompy/pencompy.py
pencompy/test.py
pencompy-0.0.4.dist-info/LICENSE
pencompy-0.0.4.dist-info/METADATA
pencompy-0.0.4.dist-info/WHEEL
pencompy-0.0.4.dist-info/top_level.txt
pencompy-0.0.4.dist-info/RECORD
