Metadata-Version: 2.1
Name: pencompy
Version: 0.0.4
Summary: Pencom relay controller over Ethernet
Home-page: https://github.com/dubnom/pencompy
Author: Michael Dubno
Author-email: michael@dubno.com
License: UNKNOWN
Platform: UNKNOWN
Classifier: Programming Language :: Python :: 3
Classifier: License :: OSI Approved :: MIT License
Classifier: Operating System :: OS Independent
